{
  "architecture": {
    "entry_point": "server/index.ts (Express server, price monitor initializer)",
    "routing": "server/routes.ts (API endpoints, user auth, position management, AI bridge)",
    "database": {
      "orm": "Drizzle ORM",
      "connection": "server/db.ts (PostgreSQL connection via Neon Serverless)",
      "storage_layer": "server/storage.ts (DatabaseStorage class for CRUD operations)",
      "schema": "@shared/schema.ts (users, positions, closedPositions, priceHistory, aiChatHistory)"
    },
    "services": {
      "price_service": "server/services/price-service.ts (Core logic for Google Sheets and Fintables Scraper)",
      "price_monitor": "server/services/price-monitor.ts (15m intervals for stocks, CRON jobs for funds)",
      "cache_layer": "server/services/fund-price-cache.ts (In-memory cache for fund prices)",
      "ai_analysis": "server/prompt.ts (System instructions for Gemini 1.5 Flash portfolio insights)"
    }
  },
  "methodology_logic": {
    "bist_stock_logic": {
      "primary": "Google Sheets JSON API (via Apps Script)",
      "fallback": "Current price from DB (positions.currentPrice) or null",
      "update_frequency": "15 minutes",
      "registration": "Auto-sends IST:SYMBOL to Sheets Webhook on creation"
    },
    "us_stock_logic": {
      "primary": "Google Sheets JSON API (via Apps Script)",
      "currency_conversion": "Frankfurter API (USD -> TRY) with 34.25 fallback",
      "fallback": "Current price from DB (positions.currentPrice) or null",
      "update_frequency": "15 minutes",
      "registration": "Auto-sends NASDAQ:SYMBOL to Sheets Webhook on creation"
    },
    "fund_logic": {
      "primary": "Fintables Scraper (via ScraperAPI)",
      "scraper_details": {
        "url_pattern": "https://fintables.com/fonlar/{symbol}",
        "proxy_config": "ScraperAPI (render=false, premium=false)",
        "timeout": "60000ms",
        "parsing_hierarchy": {
          "step_1": "Robust Regex match on '\"price\":' pattern within HTML stream data",
          "step_2_fallback": "CSS Selector 'span.inline-flex.items-center.tabular-nums'"
        },
        "optimization": "Uses render=false for 20x faster response time (~2s) and lower quota usage."
      },
      "fallback_1": "Last known price from Database",
      "fallback_2": "Returns null if no fallback available",
      "update_frequency": "Scheduled at 09:00 and 10:00 Turkey Time"
    }
  },
  "optimization_notes": {
    "zero_mock_policy": "Fiyat bulunamazsa null dönülür, asla sahte/random fiyat üretilmez.",
    "ios_pwa_ux": "Vaul DrawerModal kullanımı, visualViewport dinleyicileri ve safe-area-inset yönetimi.",
    "ai_context": "Her mesajda tüm portföy snapshot'ı (JSON) sisteme enjekte edilir.",
    "error_handling": "Fiyat hatasında AlertCircle ikonu gösterilir ve maliyet (buyPrice) üzerinden hesaplama devam eder."
  },
  "last_updated": "2026-04-25"
}
